vp4jl/_version.py
chaldene_usability_study-0.0.1.data/data/share/jupyter/labextensions/vp4jl/install.json
chaldene_usability_study-0.0.1.dist-info/METADATA
chaldene_usability_study-0.0.1.dist-info/WHEEL
chaldene_usability_study-0.0.1.dist-info/licenses/LICENSE
chaldene_usability_study-0.0.1.dist-info/RECORD
